text_template/__init__.py
text_template/text_template.py
text_template-1.0.1.dist-info/WHEEL
text_template-1.0.1.dist-info/METADATA
text_template-1.0.1.dist-info/RECORD
